docdocdoc/__init__.py
docdocdoc/build.py
docdocdoc/parts.py
docdocdoc/utils.py
docdocdoc-0.1.0.dist-info/LICENSE.txt
docdocdoc-0.1.0.dist-info/METADATA
docdocdoc-0.1.0.dist-info/WHEEL
docdocdoc-0.1.0.dist-info/top_level.txt
docdocdoc-0.1.0.dist-info/zip-safe
docdocdoc-0.1.0.dist-info/RECORD
