Metadata-Version: 2.1
Name: docdocdoc
Version: 0.1.0
Summary: A python library to template documentation from docstrings.
Home-page: http://github.com/medialab/docdocdoc
Author: Guillaume Plique, Laura Miguel
Author-email: guillaume.plique@sciencespo.fr
License: MIT
Keywords: documentation
Platform: UNKNOWN
Requires-Python: >=3.6
Requires-Dist: docstring-parser (==0.15)
